SciPyFST/__init__.py
SciPyFST/fst.py
SciPyFST/fstUtils/__init__.py
SciPyFST/fstUtils/playToWave.py
SciPyFST/fstUtils/toDot.py
SciPyFST/fstUtils/toMdTable.py
SciPyFST-0.0.4.dist-info/LICENSE
SciPyFST-0.0.4.dist-info/METADATA
SciPyFST-0.0.4.dist-info/WHEEL
SciPyFST-0.0.4.dist-info/top_level.txt
SciPyFST-0.0.4.dist-info/RECORD
