Metadata-Version: 2.1
Name: SciPyFST
Version: 0.0.4
Summary: The package perform simple operations on FST (Finite-state transducer) and visualize results obtained
Home-page: https://github.com/MorriganR/SciPyFST
Author: MorriganR
Author-email: dasha@occamlab.com
License: UNKNOWN
Project-URL: Bug Tracker, https://github.com/MorriganR/SciPyFST/issues
Platform: UNKNOWN
Classifier: Development Status :: 3 - Alpha
Classifier: Programming Language :: Python :: 3
Classifier: License :: OSI Approved :: MIT License
Classifier: Operating System :: OS Independent
Requires-Python: >=3.6
License-File: LICENSE
